beekeeper/__init__.py
beekeeper/api.py
beekeeper/comms.py
beekeeper/data_handlers.py
beekeeper/exceptions.py
beekeeper/hive.py
beekeeper/variable_handlers.py
beekeeper/variables.py
beekeeper-0.9.1.dist-info/DESCRIPTION.rst
beekeeper-0.9.1.dist-info/METADATA
beekeeper-0.9.1.dist-info/RECORD
beekeeper-0.9.1.dist-info/WHEEL
beekeeper-0.9.1.dist-info/metadata.json
beekeeper-0.9.1.dist-info/top_level.txt
